dialektik.py
dialektik-0.0.3.dist-info/METADATA
dialektik-0.0.3.dist-info/WHEEL
dialektik-0.0.3.dist-info/entry_points.txt
dialektik-0.0.3.dist-info/top_level.txt
dialektik-0.0.3.dist-info/RECORD
