Metadata-Version: 2.1
Name: dialektik
Version: 0.0.3
Summary: Merge. Synthesize. Create. Dialektik generates new content by fusing ideas from diverse sources, revealing unexpected insights and perspectives.
Home-page: https://github.com/JosefAlbers/Dialektik
Author: Josef Albers
Author-email: albersj66@gmail.com
License: MIT
Requires-Python: >=3.12.3
Requires-Dist: datasets
Requires-Dist: huggingface-hub
Requires-Dist: phi-3-vision-mlx
Requires-Dist: mlx
Requires-Dist: fire
